onelearn/__init__.py
onelearn/checks.py
onelearn/datasets/__init__.py
onelearn/datasets/data/adult.csv.zip
onelearn/datasets/data/bank.csv.zip
onelearn/datasets/data/car.csv.zip
onelearn/datasets/data/cardiotocography.csv.zip
onelearn/datasets/data/churn.csv.zip
onelearn/datasets/data/default_cb.csv.zip
onelearn/datasets/data/letter.csv.zip
onelearn/datasets/data/satimage.csv.zip
onelearn/datasets/data/sensorless.csv.zip
onelearn/datasets/data/spambase.csv.zip
onelearn/datasets/loaders.py
onelearn/datasets/regression.py
onelearn/dummy.py
onelearn/forest.py
onelearn/node_collection.py
onelearn/node_methods.py
onelearn/playground/__init__.py
onelearn/playground/playground.py
onelearn/sample.py
onelearn/tree.py
onelearn/tree_methods.py
onelearn/types.py
onelearn/utils.py
onelearn-0.3.0.dist-info/LICENSE
onelearn-0.3.0.dist-info/WHEEL
onelearn-0.3.0.dist-info/METADATA
onelearn-0.3.0.dist-info/RECORD
