Metadata-Version: 2.1
Name: onelearn
Version: 0.3.0
Summary: onelearn is a small python package for online learning
Home-page: https://onelearn.readthedocs.io
Keywords: machine-learning,online-learning-algorithms,python,random-forest,classification,regression
Author: Stéphane Gaïffas
Author-email: stephane.gaiffas@gmail.com
Requires-Python: >=3.7,<4.0
Classifier: Development Status :: 3 - Alpha
Classifier: Intended Audience :: Developers
Classifier: Intended Audience :: Science/Research
Classifier: License :: OSI Approved :: BSD License
Classifier: Operating System :: POSIX
Classifier: Operating System :: Unix
Classifier: Programming Language :: Python
Classifier: Programming Language :: Python :: 3
Classifier: Programming Language :: Python :: 3.7
Classifier: Programming Language :: Python :: 3.8
Classifier: Topic :: Software Development :: Libraries :: Python Modules
Requires-Dist: bokeh (>=1.3.4,<2.0.0)
Requires-Dist: colorcet (>=2.0.2,<3.0.0)
Requires-Dist: matplotlib (>=3.1,<4.0)
Requires-Dist: numba (>=0.51,<0.52)
Requires-Dist: numpy (>=1.17.4,<2.0.0)
Requires-Dist: scikit-learn (>=0.22,<0.23)
Requires-Dist: scipy (>=1.3.2,<2.0.0)
Requires-Dist: seaborn (>=0.9,<0.10)
Requires-Dist: streamlit (>=0.49.0,<0.50.0)
Requires-Dist: tqdm (>=4.36,<5.0)
Project-URL: Documentation, https://onelearn.readthedocs.io
Project-URL: Repository, https://github.com/onelearn/onelearn
